app/__init__.py
app/main.py
app/pages/1_DRM_Inspect.py
app/pages/2_MUL_Converter.py
app/pages/3_Bigfile_Repack.py
app/pages/4_Unit_Inspect.py
app/pages/__init__.py
pyDXHR/__init__.py
pyDXHR/Bigfile/__init__.py
pyDXHR/Bigfile/console_filenames.py
pyDXHR/Bigfile/pack.py
pyDXHR/Bigfile/read_entries.py
pyDXHR/Bigfile/read_header.py
pyDXHR/Bigfile/unpack.py
pyDXHR/Bigfile/filelist/__init__.py
pyDXHR/DRM/__init__.py
pyDXHR/DRM/resolver.py
pyDXHR/DRM/scenario.py
pyDXHR/DRM/unit.py
pyDXHR/DRM/unpack.py
pyDXHR/DRM/utils.py
pyDXHR/DRM/Database/__init__.py
pyDXHR/DRM/Database/emails.py
pyDXHR/DRM/Database/ireader.py
pyDXHR/DRM/Database/objective.py
pyDXHR/DRM/Database/pickup.py
pyDXHR/DRM/Database/scenario.py
pyDXHR/DRM/Section/CollisionMesh.py
pyDXHR/DRM/Section/FMODSoundBank.py
pyDXHR/DRM/Section/Material.py
pyDXHR/DRM/Section/RenderMesh.py
pyDXHR/DRM/Section/RenderResource.py
pyDXHR/DRM/Section/ShaderLib.py
pyDXHR/DRM/Section/__init__.py
pyDXHR/DRM/Specific/__init__.py
pyDXHR/DRM/Specific/globalscaleformdatabase.py
pyDXHR/MUL/__init__.py
pyDXHR/MUL/convert.py
pyDXHR/USM/__init__.py
pyDXHR/entrypoints/__init__.py
pyDXHR/entrypoints/bigfile_pack.py
pyDXHR/entrypoints/bigfile_unpack.py
pyDXHR/entrypoints/drm_decompress.py
pyDXHR/entrypoints/drm_pack.py
pyDXHR/entrypoints/drm_to_gltf.py
pyDXHR/entrypoints/drm_unpack.py
pyDXHR/entrypoints/material_dump.py
pyDXHR/entrypoints/mul_to_fsb.py
pyDXHR/entrypoints/usm_extract.py
pyDXHR/export/__init__.py
pyDXHR/export/dds.py
pyDXHR/export/gltf.py
pyDXHR/export/mesh.py
pyDXHR/export/unit.py
pyDXHR/generated/__init__.py
pyDXHR/generated/bigfile_header.py
pyDXHR/generated/dds.py
pyDXHR/generated/dxhr_drm.py
pyDXHR/generated/enums.py
pyDXHR/generated/locals.py
pyDXHR/generated/multiplex_stream.py
pyDXHR/generated/pcd.py
pyDXHR/generated/ps3t.py
pyDXHR/generated/render_model_buffer.py
pyDXHR/generated/render_terrain.py
pyDXHR/import/__init__.py
pyDXHR/import/dds.py
pyDXHR/locals/__init__.py
pyDXHR-1.0.0.dist-info/LICENSE
pyDXHR-1.0.0.dist-info/METADATA
pyDXHR-1.0.0.dist-info/WHEEL
pyDXHR-1.0.0.dist-info/entry_points.txt
pyDXHR-1.0.0.dist-info/top_level.txt
pyDXHR-1.0.0.dist-info/RECORD
